markdown_inline_mermaid.py
markdown_inline_mermaid-1.0.3.dist-info/LICENSE
markdown_inline_mermaid-1.0.3.dist-info/METADATA
markdown_inline_mermaid-1.0.3.dist-info/WHEEL
markdown_inline_mermaid-1.0.3.dist-info/top_level.txt
markdown_inline_mermaid-1.0.3.dist-info/RECORD
