Metadata-Version: 2.1
Name: markdown-inline-mermaid
Version: 1.0.3
Summary: Render inline graphs with Markdown and Mermaid
Home-page: https://github.com/johanneswuerbach/markdown-inline-mermaid
Author: Johannes Wuerbach
Author-email: johannes.wuerbach@googlemail.com
License: MIT
Classifier: Development Status :: 5 - Production/Stable
Classifier: Intended Audience :: Developers
Classifier: Topic :: Documentation
Classifier: Topic :: Text Processing
Classifier: License :: OSI Approved :: MIT License
Classifier: Programming Language :: Python :: 3
Classifier: Programming Language :: Python :: 3.7
Classifier: Programming Language :: Python :: 3.8
Classifier: Programming Language :: Python :: 3.9
Classifier: Programming Language :: Python :: 3.10
Classifier: Programming Language :: Python :: 3.11
License-File: LICENSE
Requires-Dist: Markdown (>=2.3.1)
